acroplans_branding/__init__.py
acroplans_branding/components.py
acroplans_branding/styling.py
acroplans_branding/assets/logo.png
acroplans_branding-0.1.0.dist-info/licenses/LICENSE
acroplans_branding-0.1.0.dist-info/METADATA
acroplans_branding-0.1.0.dist-info/WHEEL
acroplans_branding-0.1.0.dist-info/top_level.txt
acroplans_branding-0.1.0.dist-info/RECORD
