Metadata-Version: 2.4
Name: acroplans-branding
Version: 0.1.0
Summary: Branding package for Acroplans Hugging Face spaces
Author-email: Krishnarao-Acroplans-Official <krishnarao@acroplans.com>
License: Proprietary
Project-URL: Homepage, https://github.com/Krishnarao-Acroplans-Official/acroplans-branding
Classifier: Programming Language :: Python :: 3
Classifier: Operating System :: OS Independent
Requires-Python: >=3.10
License-File: LICENSE
Requires-Dist: streamlit>=1.0.0
Requires-Dist: pillow>=8.0.0
Requires-Dist: requests>=2.25.0
Dynamic: license-file
